{"code":0,"info":[{"carCategoryName":"EÃÀ","carCategoryId":14451,"parentId":1047,"carCategoryType":2,"series":"EÃÀ","manufacturer":"¹ãÆû¼ª°Â"},{"carCategoryName":"GP150","carCategoryId":16669,"parentId":1047,"carCategoryType":2,"series":"GP150","manufacturer":"¹ãÆû¼ª°Â"},{"carCategoryName":"GS50","carCategoryId":16976,"parentId":1047,"carCategoryType":2,"series":"GS50","manufacturer":"¹ãÆû¼ª°Â"},{"carCategoryName":"GX6","carCategoryId":17362,"parentId":1047,"carCategoryType":2,"series":"GX6","manufacturer":"¹ãÆû¼ª°Â"},{"carCategoryName":"ÒÁÃÀ","carCategoryId":33814,"parentId":1047,"carCategoryType":2,"series":"ÒÁÃÀ","manufacturer":"¹ãÆû¼ª°Â"},{"carCategoryName":"¿­ĞıSUV","carCategoryId":35493,"parentId":1047,"carCategoryType":2,"series":"¿­ĞıSUV","manufacturer":"¹ãÆû¼ª°Â"},{"carCategoryName":"¿­î£","carCategoryId":35629,"parentId":1047,"carCategoryType":2,"series":"¿­î£","manufacturer":"¹ãÆû¼ª°Â"},{"carCategoryName":"°ÂĞùG3","carCategoryId":43742,"parentId":1047,"carCategoryType":2,"series":"°ÂĞù","manufacturer":"¹ãÆû¼ª°Â"},{"carCategoryName":"°ÂĞùG5","carCategoryId":43760,"parentId":1047,"carCategoryType":2,"series":"°ÂĞù","manufacturer":"¹ãÆû¼ª°Â"},{"carCategoryName":"°ÂĞùGX5","carCategoryId":43829,"parentId":1047,"carCategoryType":2,"series":"°ÂĞù","manufacturer":"¹ãÆû¼ª°Â"},{"carCategoryName":"Ë§Áè","carCategoryId":46894,"parentId":1047,"carCategoryType":2,"series":"Ë§Áè","manufacturer":"¹ãÆû¼ª°Â"},{"carCategoryName":"Ë§Íş","carCategoryId":46901,"parentId":1047,"carCategoryType":2,"series":"Ë§Íş","manufacturer":"¹ãÆû¼ª°Â"},{"carCategoryName":"Ë§½¢","carCategoryId":47016,"parentId":1047,"carCategoryType":2,"series":"Ë§½¢","manufacturer":"¹ãÆû¼ª°Â"},{"carCategoryName":"Ë§±ª","carCategoryId":47062,"parentId":1047,"carCategoryType":2,"series":"Ë§±ª","manufacturer":"¹ãÆû¼ª°Â"},{"carCategoryName":"Ë§³Û","carCategoryId":47097,"parentId":1047,"carCategoryType":2,"series":"Ë§³Û","manufacturer":"¹ãÆû¼ª°Â"},{"carCategoryName":"ĞÇÍú","carCategoryId":54252,"parentId":1047,"carCategoryType":2,"series":"ĞÇÍú","manufacturer":"¹ãÆû¼ª°Â"},{"carCategoryName":"ĞÇÍúCL","carCategoryId":54322,"parentId":1047,"carCategoryType":2,"series":"ĞÇÍú","manufacturer":"¹ãÆû¼ª°Â"},{"carCategoryName":"ĞÇÍúL","carCategoryId":54345,"parentId":1047,"carCategoryType":2,"series":"ĞÇÍú","manufacturer":"¹ãÆû¼ª°Â"},{"carCategoryName":"ĞÇÍúM1","carCategoryId":54359,"parentId":1047,"carCategoryType":2,"series":"ĞÇÍú","manufacturer":"¹ãÆû¼ª°Â"},{"carCategoryName":"ĞÇÍúM2","carCategoryId":54373,"parentId":1047,"carCategoryType":2,"series":"ĞÇÍú","manufacturer":"¹ãÆû¼ª°Â"},{"carCategoryName":"ĞÇÀÊ","carCategoryId":54387,"parentId":1047,"carCategoryType":2,"series":"ĞÇÀÊ","manufacturer":"¹ãÆû¼ª°Â"},{"carCategoryName":"²ÆÔË100","carCategoryId":72472,"parentId":1047,"carCategoryType":2,"series":"²ÆÔË","manufacturer":"¹ãÆû¼ª°Â"},{"carCategoryName":"²ÆÔË300","carCategoryId":72584,"parentId":1047,"carCategoryType":2,"series":"²ÆÔË","manufacturer":"¹ãÆû¼ª°Â"},{"carCategoryName":"²ÆÔË500","carCategoryId":72628,"parentId":1047,"carCategoryType":2,"series":"²ÆÔË","manufacturer":"¹ãÆû¼ª°Â"}],"msg":"³É¹¦"}